bibpublish/__init__.py
bibpublish/cli.py
bibpublish/entry.py
bibpublish/template.py
bibpublish/templates/__init__.py
bibpublish/templates/latex/__init__.py
bibpublish/templates/latex/article-entry.tmpl
bibpublish/templates/latex/article-foot.tmpl
bibpublish/templates/latex/article-head.tmpl
bibpublish/templates/latex/book-entry.tmpl
bibpublish/templates/latex/book-foot.tmpl
bibpublish/templates/latex/book-head.tmpl
bibpublish/templates/latex/foot.tmpl
bibpublish/templates/latex/head.tmpl
bibpublish/templates/latex/incollection-entry.tmpl
bibpublish/templates/latex/incollection-foot.tmpl
bibpublish/templates/latex/incollection-head.tmpl
bibpublish/templates/latex/inproceedings-entry.tmpl
bibpublish/templates/latex/inproceedings-foot.tmpl
bibpublish/templates/latex/inproceedings-head.tmpl
bibpublish/templates/latex/mastersthesis-entry.tmpl
bibpublish/templates/latex/mastersthesis-foot.tmpl
bibpublish/templates/latex/mastersthesis-head.tmpl
bibpublish/templates/latex/phdthesis-entry.tmpl
bibpublish/templates/latex/phdthesis-foot.tmpl
bibpublish/templates/latex/phdthesis-head.tmpl
bibpublish/templates/snf/__init__.py
bibpublish/templates/snf/article-entry.tmpl
bibpublish/templates/snf/article-foot.tmpl
bibpublish/templates/snf/article-head.tmpl
bibpublish/templates/snf/book-entry.tmpl
bibpublish/templates/snf/book-foot.tmpl
bibpublish/templates/snf/book-head.tmpl
bibpublish/templates/snf/foot.tmpl
bibpublish/templates/snf/head.tmpl
bibpublish/templates/snf/incollection-entry.tmpl
bibpublish/templates/snf/incollection-foot.tmpl
bibpublish/templates/snf/incollection-head.tmpl
bibpublish/templates/snf/inproceedings-entry.tmpl
bibpublish/templates/snf/inproceedings-foot.tmpl
bibpublish/templates/snf/inproceedings-head.tmpl
bibpublish/templates/snf/techreport-entry.tmpl
bibpublish/templates/snf/techreport-foot.tmpl
bibpublish/templates/snf/techreport-head.tmpl
bibpublish/templates/snf/unpublished-entry.tmpl
bibpublish/templates/snf/unpublished-foot.tmpl
bibpublish-1.0.1.dist-info/LICENSE
bibpublish-1.0.1.dist-info/METADATA
bibpublish-1.0.1.dist-info/WHEEL
bibpublish-1.0.1.dist-info/entry_points.txt
bibpublish-1.0.1.dist-info/RECORD
