Metadata-Version: 2.1
Name: bibpublish
Version: 1.0.1
Summary: bibpublish - publishes bibTex bibliographies.
Home-page: http://github.com/AlbertWeichselbraun/bibPublish
License: GPL-3.0
Keywords: bibPublish,bibtex,publish
Author: Albert Weichselbraun
Author-email: albert@weichselbraun.net
Requires-Python: >=3.8,<4.0
Classifier: License :: OSI Approved :: GNU General Public License v3 (GPLv3)
Classifier: Programming Language :: Python :: 3
Classifier: Programming Language :: Python :: 3.8
Classifier: Programming Language :: Python :: 3.9
Classifier: Programming Language :: Python :: 3.10
Classifier: Programming Language :: Python :: 3.11
Classifier: Programming Language :: Python :: 3.12
Requires-Dist: bibtexparser (>=1.4.2,<2.0.0)
Project-URL: Repository, http://github.com/AlbertWeichselbraun/bibPublish
